odoo/addons/mail_server_filter/LICENSE
odoo/addons/mail_server_filter/README.rst
odoo/addons/mail_server_filter/__init__.py
odoo/addons/mail_server_filter/__manifest__.py
odoo/addons/mail_server_filter/images/screen.png
odoo/addons/mail_server_filter/models/__init__.py
odoo/addons/mail_server_filter/models/fetchmail_server.py
odoo/addons/mail_server_filter/models/ir_mail_server.py
odoo/addons/mail_server_filter/static/description/icon.png
odoo/addons/mail_server_filter/static/description/index.html
odoo/addons/mail_server_filter/tests/TEST_INSTRUCTIONS.rst
odoo/addons/mail_server_filter/views/fetchmail_server.xml
odoo/addons/mail_server_filter/views/ir_mail_server.xml
odoo_addon_mail_server_filter-18.0.1.0.0.10.dist-info/METADATA
odoo_addon_mail_server_filter-18.0.1.0.0.10.dist-info/WHEEL
odoo_addon_mail_server_filter-18.0.1.0.0.10.dist-info/top_level.txt
odoo_addon_mail_server_filter-18.0.1.0.0.10.dist-info/RECORD
